potodo/__init__.py
potodo/__main__.py
potodo/arguments_handling.py
potodo/forge_api.py
potodo/json.py
potodo/logging.py
potodo/merge.py
potodo/po_file.py
potodo/potodo.py
potodo-0.35.dist-info/licenses/LICENSE
potodo-0.35.dist-info/METADATA
potodo-0.35.dist-info/WHEEL
potodo-0.35.dist-info/entry_points.txt
potodo-0.35.dist-info/top_level.txt
potodo-0.35.dist-info/RECORD
