Metadata-Version: 2.4
Name: potodo
Version: 0.35
Summary: List .po files to be translated.
Author-email: Jules Lasne <jules.lasne@gmail.com>, Maciej Olko <maciej.olko@gmail.com>, Julien Palard <julien@palard.fr>
License-Expression: MIT
Project-URL: Homepage, https://git.afpy.org/AFPy/potodo
Keywords: potodo,gettext,i18n
Classifier: Development Status :: 5 - Production/Stable
Classifier: Intended Audience :: Developers
Classifier: Natural Language :: English
Classifier: Programming Language :: Python :: 3
Requires-Python: >=3.10
License-File: LICENSE
Requires-Dist: colorama>=0.4.6
Requires-Dist: gitignore-parser
Requires-Dist: polib
Requires-Dist: requests
Requires-Dist: simple-term-menu
Provides-Extra: dev
Requires-Dist: black; extra == "dev"
Requires-Dist: coverage; extra == "dev"
Requires-Dist: mypy; extra == "dev"
Requires-Dist: pytest; extra == "dev"
Requires-Dist: tox; extra == "dev"
Requires-Dist: types-requests; extra == "dev"
Requires-Dist: types-polib; extra == "dev"
Requires-Dist: pylint; extra == "dev"
Dynamic: license-file
